tlds/__init__.py
tlds/main.py
tlds/test_main.py
gladhost_tlds-1.0.5.dist-info/METADATA
gladhost_tlds-1.0.5.dist-info/WHEEL
gladhost_tlds-1.0.5.dist-info/top_level.txt
gladhost_tlds-1.0.5.dist-info/RECORD
