Metadata-Version: 2.4
Name: gladhost-tlds
Version: 1.0.5
Summary: library to retrieve and validate domain's TLD
License-Expression: MPL-2.0
Keywords: tld,tld list,tlds,domain tld
Classifier: Programming Language :: Python :: 3
Requires-Python: >=3.10
